uncoupled/__init__.py
uncoupled/container.py
uncoupled/exception.py
uncoupled/lifetime.py
uncoupled/py.typed
uncoupled/providers/__init__.py
uncoupled/providers/provider.py
uncoupled/providers/scoped.py
uncoupled/providers/singleton.py
uncoupled/providers/transient.py
uncoupled-0.1.1.dist-info/METADATA
uncoupled-0.1.1.dist-info/WHEEL
uncoupled-0.1.1.dist-info/licenses/LICENSE
uncoupled-0.1.1.dist-info/RECORD
