Metadata-Version: 2.3
Name: uncoupled
Version: 0.1.1
Summary: Modern Dependency Injection Container for Python 3.12+
Requires-Python: >=3.12
